LICENSE
MANIFEST.in
README.md
setup.py
./src/kPointLattice.cpp
./src/kPointLatticeGenerator.cpp
./src/msmath.cpp
demo_kplib/CMakeLists.txt
demo_kplib/include/spglib.h
demo_kplib/lib/libsymspg.a
demo_kplib/src/main.cpp
demo_kplib/src/poscar.cpp
demo_kplib/src/poscar.h
demo_kplib/src/precalc.cpp
demo_kplib/src/precalc.h
demo_kplib/src/utils.cpp
demo_kplib/src/utils.h
python/kpLib/__init__.py
python/kpLib/cli.py
python/kpLib/interface.cpp
python/kpLib/interface.py
python/kpLib.egg-info/PKG-INFO
python/kpLib.egg-info/SOURCES.txt
python/kpLib.egg-info/dependency_links.txt
python/kpLib.egg-info/entry_points.txt
python/kpLib.egg-info/not-zip-safe
python/kpLib.egg-info/requires.txt
python/kpLib.egg-info/top_level.txt
src/kPointLattice.cpp
src/kPointLattice.h
src/kPointLatticeGenerator.cpp
src/kPointLatticeGenerator.h
src/msmath.cpp
src/msmath.h
src/msmath.ipp