Metadata-Version: 2.1
Name: kpLib
Version: 1.1.1
Summary: Library for generating highly-efficient generalized Monkhorst-Pack K-point grids to accelerate electronic structure calculations, like DFT.
Home-page: https://gitlab.com/muellergroup/kplib
Author: Yunzhe Wang
Author-email: ywang393@jhu.edu
License: Apache-2.0
Keywords: Computational Materials Science,Materials Simulation,Electronic Structure,K-points,kpoint,Density Functional Theory,DFT,VASP,Crystal
Classifier: Programming Language :: Python :: 3
Classifier: Programming Language :: Python :: 3.7
Classifier: Programming Language :: Python :: 3.8
Classifier: Programming Language :: Python :: 3.9
Classifier: Development Status :: 5 - Production/Stable
Classifier: Intended Audience :: Science/Research
Classifier: License :: OSI Approved :: Apache Software License
Classifier: Operating System :: OS Independent
Classifier: Topic :: Scientific/Engineering :: Information Analysis
Classifier: Topic :: Scientific/Engineering :: Physics
Classifier: Topic :: Software Development :: Libraries :: Python Modules
Provides-Extra: tests
Provides-Extra: cli
License-File: LICENSE
